git_revision_graph/__init__.py
git_revision_graph/__main__.py
git_revision_graph-0.0.6.dist-info/LICENSE
git_revision_graph-0.0.6.dist-info/METADATA
git_revision_graph-0.0.6.dist-info/WHEEL
git_revision_graph-0.0.6.dist-info/entry_points.txt
git_revision_graph-0.0.6.dist-info/RECORD
