Metadata-Version: 2.1
Name: git-revision-graph
Version: 0.0.6
Summary: Generate revision graph like TortoiseGit did for chosen branches
Home-page: https://github.com/chaoqing/git-revision-graph
License: AGPL
Keywords: git,graph
Author: chaoqing
Author-email: chaoqingwang.nick@gmail.com
Requires-Python: >=3.8,<4.0
Classifier: Development Status :: 3 - Alpha
Classifier: Intended Audience :: Developers
Classifier: License :: OSI Approved :: MIT License
Classifier: License :: Other/Proprietary License
Classifier: Operating System :: OS Independent
Classifier: Programming Language :: Python :: 3
Classifier: Programming Language :: Python :: 3.8
Classifier: Programming Language :: Python :: 3.9
Classifier: Programming Language :: Python :: 3.10
Classifier: Programming Language :: Python :: 3.11
Classifier: Programming Language :: Python :: 3.12
Classifier: Programming Language :: Python :: 3.13
Classifier: Topic :: Software Development :: Libraries :: Python Modules
Requires-Dist: graphviz (>=0.20.3,<0.21.0)
Project-URL: Repository, https://github.com/chaoqing/git-revision-graph
